CHANGELOG.rst
blacksmith-5.0.1.dist-info/METADATA
blacksmith-5.0.1.dist-info/WHEEL
blacksmith-5.0.1.dist-info/entry_points.txt
blacksmith-5.0.1.dist-info/licenses/LICENSE
blacksmith/__init__.py
blacksmith/adapters/__init__.py
blacksmith/domain/__init__.py
blacksmith/domain/error.py
blacksmith/domain/exceptions.py
blacksmith/domain/model/__init__.py
blacksmith/domain/model/http.py
blacksmith/domain/model/middleware/__init__.py
blacksmith/domain/model/middleware/circuit_breaker.py
blacksmith/domain/model/middleware/http_cache.py
blacksmith/domain/model/middleware/prometheus.py
blacksmith/domain/model/middleware/zipkin.py
blacksmith/domain/model/params.py
blacksmith/domain/registry.py
blacksmith/domain/scanner.py
blacksmith/domain/typing.py
blacksmith/middleware/__init__.py
blacksmith/middleware/_async/__init__.py
blacksmith/middleware/_async/auth.py
blacksmith/middleware/_async/base.py
blacksmith/middleware/_async/circuit_breaker.py
blacksmith/middleware/_async/http_cache.py
blacksmith/middleware/_async/prometheus.py
blacksmith/middleware/_async/zipkin.py
blacksmith/middleware/_sync/__init__.py
blacksmith/middleware/_sync/auth.py
blacksmith/middleware/_sync/base.py
blacksmith/middleware/_sync/circuit_breaker.py
blacksmith/middleware/_sync/http_cache.py
blacksmith/middleware/_sync/prometheus.py
blacksmith/middleware/_sync/zipkin.py
blacksmith/py.typed
blacksmith/sd/__init__.py
blacksmith/sd/_async/__init__.py
blacksmith/sd/_async/adapters/__init__.py
blacksmith/sd/_async/adapters/consul.py
blacksmith/sd/_async/adapters/nomad.py
blacksmith/sd/_async/adapters/router.py
blacksmith/sd/_async/adapters/static.py
blacksmith/sd/_async/base.py
blacksmith/sd/_sync/__init__.py
blacksmith/sd/_sync/adapters/__init__.py
blacksmith/sd/_sync/adapters/consul.py
blacksmith/sd/_sync/adapters/nomad.py
blacksmith/sd/_sync/adapters/router.py
blacksmith/sd/_sync/adapters/static.py
blacksmith/sd/_sync/base.py
blacksmith/service/__init__.py
blacksmith/service/_async/__init__.py
blacksmith/service/_async/adapters/__init__.py
blacksmith/service/_async/adapters/httpx.py
blacksmith/service/_async/base.py
blacksmith/service/_async/client.py
blacksmith-5.0.1.dist-info/RECORD
