Metadata-Version: 2.1
Name: Blacksmith
Version: 5.0.1
Summary: REST API Client designed for microservices
Author-Email: Guillaume Gauvrit <guillaume@gauvr.it>
License: MIT License
Classifier: Development Status :: 5 - Production/Stable
Classifier: Framework :: AsyncIO
Classifier: Intended Audience :: Developers
Classifier: Intended Audience :: Information Technology
Classifier: License :: OSI Approved :: MIT License
Classifier: Topic :: Internet :: WWW/HTTP
Classifier: Topic :: Software Development :: Libraries
Classifier: Topic :: System :: Networking
Classifier: Typing :: Typed
Project-URL: Homepage, https://mardiros.github.io/blacksmith
Project-URL: Documentation, https://mardiros.github.io/blacksmith
Project-URL: Repository, https://github.com/mardiros/blacksmith.git
Project-URL: Issues, https://github.com/mardiros/blacksmith/issues
Project-URL: Changelog, https://mardiros.github.io/blacksmith/user/changelog.html
Requires-Python: >=3.10
Requires-Dist: httpx>=0.28
Requires-Dist: purgatory>=2.0.0
Requires-Dist: pydantic>=2.6.0
Requires-Dist: result<1,>=0.11.0
Provides-Extra: http-cache-async
Requires-Dist: redis<6,>=5.0.4; extra == "http-cache-async"
Provides-Extra: http-cache-sync
Requires-Dist: redis<6,>=5.0.4; extra == "http-cache-sync"
Provides-Extra: prometheus
Requires-Dist: prometheus-client<1,>=0.19.0; extra == "prometheus"
Provides-Extra: docs
Requires-Dist: sphinx>=7.0.0; extra == "docs"
Requires-Dist: sphinx-autodoc-typehints<2,>=1.12.0; extra == "docs"
Requires-Dist: furo>=2024.8.6; extra == "docs"
